octopusserver/Http/Router/Request.py
octopusserver/Http/Router/Response.py
octopusserver/Http/Router/Router.py
octopusserver/Http/Router/__init__.py
octopusserver/Http/Server.py
octopusserver/Http/__init__.py
octopusserver/Utils/Http.py
octopusserver/Utils/Queue.py
octopusserver/Utils/__init__.py
octopusserver/__init__.py
octopusserver-0.1.4.dist-info/WHEEL
octopusserver-0.1.4.dist-info/METADATA
octopusserver-0.1.4.dist-info/RECORD
