Metadata-Version: 2.1
Name: octopusserver
Version: 0.1.4
Summary: 
Home-page: https://github.com/pab-h/octopusserver
Author: pab-h
Author-email: dev.pab.2020@gmail.com
Requires-Python: >=3.10,<4.0
Classifier: Programming Language :: Python :: 3
Classifier: Programming Language :: Python :: 3.10
Classifier: Programming Language :: Python :: 3.11
Project-URL: Repository, https://github.com/pab-h/octopusserver
